6.4/design_6_4.v
`timescale 1ns/1ps

module design_6_4(
    input clk,
    input w,
    input reset,
    output reg z
);

    reg [3:0] s [0:15]; 
    reg [3:0] current_state, next_state;

    initial begin
        for (integer i = 0; i < 16; i++)
            s[i] = i;
    end
    always @(posedge clk) begin
        if (reset)
            current_state <= 4'b0000;
        else
            current_state <= next_state;
    end
    always @(*) begin
        z = 0;
        case (current_state)
            0: next_state = (w) ? s[1] : s[0];
            1: next_state = (w) ? s[3] : s[2];
            2: next_state = (w) ? s[5] : s[4];
            3: next_state = (w) ? s[7] : s[6];
            4: next_state = (w) ? s[9] : s[8];
            5: next_state = (w) ? s[11] : s[10];
            6: next_state = (w) ? s[13] : s[12];
            7: next_state = (w) ? s[15] : s[14];
            8: next_state = (w) ? s[1] : s[0];
            9: begin
                z = 1;
                next_state = (w) ? s[3] : s[2];
            end
            10: next_state = (w) ? s[5] : s[4];
            11: next_state = (w) ? s[7] : s[6];
            12: next_state = (w) ? s[9] : s[8];
            13: next_state = (w) ? s[11] : s[10];
            14: next_state = (w) ? s[13] : s[12];
            15: begin
                z = 1;
                next_state = (w) ? s[15] : s[14];
            end
            default: next_state = s[0];
        endcase
    end
endmodule

6.4/tb_6_4.v
`timescale 1ns/1ps

module tb_design_6_4;

    reg clk;
    reg w;
    reg reset;
    wire z;

    design_6_4 dut (
        .clk(clk),
        .w(w),
        .reset(reset),
        .z(z)
    );

    always #5 clk = ~clk;

    initial begin
        $dumpfile("wavefile.vcd");
        $dumpvars(0, tb_design_6_4);
        clk = 0;
        reset = 1;
        w = 0;
        #10;

        reset = 0; 
        #10;
        w = 0; #10;
        w = 1; #10;
        w = 0; #10;
        w = 1; #10;
        w = 1; #10;
        w = 1; #10;
        w = 1; #10;
        w = 0; #10;
        w = 0; #10;
        w = 1; #10;
        w = 0; #10;
        w = 0; #10;
        w = 1; #10;
        w = 1; #10;
        w = 1; #10;
        w = 1; #10;
        w = 1; #10;
        w = 1; #10;

        $finish;
    end

    always @(posedge clk) begin
        $display("w=%b | z=%b", w, z);
    end

endmodule

6.4/wavefile.vcd
$date
	Fri Feb 21 23:27:55 2025
$end
$version
	Icarus Verilog
$end
$timescale
	1ps
$end
$scope module tb_design_6_4 $end
$var wire 1 ! z $end
$var reg 1 " clk $end
$var reg 1 # reset $end
$var reg 1 $ w $end
$scope module dut $end
$var wire 1 " clk $end
$var wire 1 # reset $end
$var wire 1 $ w $end
$var reg 4 % current_state [3:0] $end
$var reg 4 & next_state [3:0] $end
$var reg 1 ! z $end
$scope begin $ivl_for_loop0 $end
$var integer 32 ' i [31:0] $end
$upscope $end
$upscope $end
$upscope $end
$enddefinitions $end
#0
$dumpvars
b10000 '
b0 &
bx %
0$
1#
0"
0!
$end
#5000
b0 %
1"
#10000
0"
0#
#15000
1"
#20000
0"
#25000
1"
#30000
b1 &
0"
1$
#35000
b11 &
b1 %
1"
#40000
b10 &
0"
0$
#45000
b100 &
b10 %
1"
#50000
b101 &
0"
1$
#55000
b1011 &
b101 %
1"
#60000
0"
#65000
b111 &
b1011 %
1"
#70000
0"
#75000
b1111 &
b111 %
1"
#80000
0"
#85000
1!
b1111 %
1"
#90000
b1110 &
1!
0"
0$
#95000
b1100 &
0!
b1110 %
1"
#100000
0"
#105000
b1000 &
b1100 %
1"
#110000
b1001 &
0"
1$
#115000
b11 &
1!
b1001 %
1"
#120000
b10 &
1!
0"
0$
#125000
b100 &
0!
b10 %
1"
#130000
0"
#135000
b1000 &
b100 %
1"
#140000
b1001 &
0"
1$
#145000
b11 &
1!
b1001 %
1"
#150000
0"
#155000
b111 &
0!
b11 %
1"
#160000
0"
#165000
b1111 &
b111 %
1"
#170000
0"
#175000
1!
b1111 %
1"
